vallex/__init__.py
vallex/__version__
vallex/cli/__init__.py
vallex/cli/commands/__init__.py
vallex/cli/commands/grep.py
vallex/cli/commands/gui.py
vallex/cli/commands/hist.py
vallex/cli/commands/release.py
vallex/cli/commands/scripts.py
vallex/cli/commands/show.py
vallex/cli/commands/web.py
vallex/cli/common.py
vallex/cli/completion.py
vallex/cli/lib.py
vallex/config.py
vallex/data_structures/__init__.py
vallex/data_structures/attribs.py
vallex/data_structures/collections.py
vallex/data_structures/constants.py
vallex/data_structures/lexical_unit.py
vallex/data_structures/utils.py
vallex/error.py
vallex/example-pyvallex.ini
vallex/grep.py
vallex/gui/__init__.py
vallex/gui/app_menu.py
vallex/gui/bridge.py
vallex/gui/debug.py
vallex/gui/main_window.py
vallex/gui/qtutils.py
vallex/gui/status.py
vallex/gui/tab_widget.py
vallex/json_utils.py
vallex/location.py
vallex/log.py
vallex/main.py
vallex/pyvallex.ico
vallex/release_key.pub
vallex/scripts/__init__.py
vallex/scripts/dynamic_properties/misc_info.py
vallex/scripts/mapreduce.py
vallex/scripts/mapreducers/slovko.py
vallex/scripts/tests/misc_tests.py
vallex/scripts/tests/noun_tests.py
vallex/scripts/tests/verb_tests.py
vallex/scripts/transforms/add_parent_id.py
vallex/scripts/transforms/add_valdiff.py
vallex/scripts/utils.py
vallex/server/__init__.py
vallex/server/app_state.py
vallex/server/bottle_utils.py
vallex/server/db_migrations/__init__.py
vallex/server/frontend/dist/favicon.ico
vallex/server/frontend/dist/index.html
vallex/server/frontend/dist/static/css/app.9aa92b2b.css
vallex/server/frontend/dist/static/css/chunk-vendors.d08a7c2d.css
vallex/server/frontend/dist/static/fonts/MaterialIcons-Regular.0509ab09.woff2
vallex/server/frontend/dist/static/fonts/MaterialIcons-Regular.29b882f0.woff
vallex/server/frontend/dist/static/fonts/MaterialIcons-Regular.96c47680.eot
vallex/server/frontend/dist/static/fonts/MaterialIcons-Regular.da4ea5cd.ttf
vallex/server/frontend/dist/static/js/app.5187940b.js
vallex_tools-0.12.dist-info/entry_points.txt
vallex_tools-0.12.dist-info/LICENSE
vallex_tools-0.12.dist-info/WHEEL
vallex_tools-0.12.dist-info/METADATA
vallex_tools-0.12.dist-info/RECORD
