Metadata-Version: 2.1
Name: vallex-tools
Version: 0.12
Summary: A Python interface for working with vallency lexicon data.
Home-page: https://verner.gitlab.io/pyvallex/
License: MIT
Keywords: nlp,lexicon,valency
Author: Jonathan L. Verner
Author-email: jonathan.verner@matfyz.cz
Requires-Python: >=3.6
Classifier: Environment :: Console
Classifier: Environment :: Web Environment
Classifier: Environment :: Win32 (MS Windows)
Classifier: Environment :: X11 Applications :: Qt
Classifier: Intended Audience :: Science/Research
Classifier: License :: OSI Approved :: MIT License
Classifier: Operating System :: OS Independent
Classifier: Programming Language :: Python :: 3
Classifier: Programming Language :: Python :: 3.6
Classifier: Programming Language :: Python :: 3.7
Classifier: Programming Language :: Python :: 3.8
Classifier: Topic :: Scientific/Engineering :: Artificial Intelligence
Classifier: Topic :: Text Processing :: Linguistic
Provides-Extra: server
Provides-Extra: updater
Requires-Dist: bsdiff4 (==1.1.5); extra == "updater"
Requires-Dist: gunicorn (>=20.0.4,<21.0.0); extra == "server"
Requires-Dist: jinja2
Requires-Dist: pynacl; extra == "updater"
Requires-Dist: pyqt5 (==5.14.1)
Requires-Dist: pyqtwebengine (==5.14)
Requires-Dist: setproctitle (>=1.1.10,<2.0.0); extra == "server"
Project-URL: Documentation, https://verner.gitlab.io/pyvallex/
Project-URL: Demo (readonly), http://quest.ms.mff.cuni.cz/nomvallex/
Project-URL: Repository, https://gitlab.com/Verner/pyvallex
